xwrf/__init__.py
xwrf/accessors.py
xwrf/config.py
xwrf/config.yaml
xwrf/destagger.py
xwrf/grid.py
xwrf/postprocess.py
xwrf/tutorial.py
xwrf/unit_harmonization_map.yaml
xwrf/version_report.py
xwrf-0.0.5.dist-info/licenses/LICENSE
xwrf-0.0.5.dist-info/METADATA
xwrf-0.0.5.dist-info/WHEEL
xwrf-0.0.5.dist-info/top_level.txt
xwrf-0.0.5.dist-info/RECORD
