Metadata-Version: 2.4
Name: xwrf
Version: 0.0.5
Summary: A lightweight interface for working with the Weather Research and Forecasting (WRF) model output in Xarray.
Home-page: https://xwrf.readthedocs.io
Maintainer: xWRF Developers
License: Apache 2.0
Project-URL: Documentation, https://xwrf.readthedocs.io
Project-URL: Source, https://github.com/xarray-contrib/xwrf
Project-URL: Tracker, https://github.com/xarray-contrib/xwrf/issues
Project-URL: Discussions/Support, https://github.com/xarray-contrib/xwrf/discussions
Keywords: wrf,xarray
Classifier: Development Status :: 4 - Beta
Classifier: License :: OSI Approved :: Apache Software License
Classifier: Operating System :: OS Independent
Classifier: Intended Audience :: Science/Research
Classifier: Programming Language :: Python
Classifier: Programming Language :: Python :: 3
Classifier: Programming Language :: Python :: 3.10
Classifier: Programming Language :: Python :: 3.11
Classifier: Programming Language :: Python :: 3.12
Classifier: Topic :: Scientific/Engineering
Requires-Python: >=3.10
License-File: LICENSE
Requires-Dist: xarray!=0.20.0,!=0.20.1,>=0.18
Requires-Dist: donfig>=0.6.0
Requires-Dist: pyproj>=2.4.1
Dynamic: classifier
Dynamic: description
Dynamic: description-content-type
Dynamic: home-page
Dynamic: keywords
Dynamic: license
Dynamic: license-file
Dynamic: maintainer
Dynamic: project-url
Dynamic: requires-dist
Dynamic: requires-python
Dynamic: summary
